giji-0.4.0.data/data/pyproject.toml
src/.DS_Store
src/__init__.py
src/cli.py
src/config.py
src/ai/base.py
src/cz_ai_conventional/__init__.py
src/cz_ai_conventional/cli.py
src/cz_ai_conventional/cz_ai_conventional.py
src/cz_ai_conventional/version.py
src/jira/__init__.py
src/jira/cli.py
src/jira/config.py
src/jira/gemini_utils.py
src/jira/service.py
src/pr_summary/__init__.py
src/pr_summary/cli.py
src/pr_summary/gemini_utils.py
src/pr_summary/git_utils.py
src/pr_summary/utils.py
src/slack/__init__.py
src/slack/cli.py
src/slack/client.py
giji-0.4.0.dist-info/LICENSE
giji-0.4.0.dist-info/METADATA
giji-0.4.0.dist-info/WHEEL
giji-0.4.0.dist-info/entry_points.txt
giji-0.4.0.dist-info/top_level.txt
giji-0.4.0.dist-info/RECORD
