Metadata-Version: 2.2
Name: giji
Version: 0.4.0
Summary: Git tools for Commitizen and PR Summary Generation using AI
Home-page: https://github.com/cometa/giji
Author: Cometa
Author-email: Cometa <apps@getcometa.com>
License: MIT
Project-URL: Homepage, https://github.com/cometa/giji
Project-URL: Bug Tracker, https://github.com/cometa/giji/issues
Classifier: Development Status :: 3 - Alpha
Classifier: Intended Audience :: Developers
Classifier: Topic :: Software Development :: Version Control :: Git
Classifier: Programming Language :: Python :: 3
Classifier: Programming Language :: Python :: 3.7
Classifier: Programming Language :: Python :: 3.8
Classifier: Programming Language :: Python :: 3.9
Classifier: Programming Language :: Python :: 3.10
Classifier: Programming Language :: Python :: 3.11
Classifier: License :: OSI Approved :: MIT License
Classifier: Operating System :: OS Independent
Requires-Python: >=3.7
License-File: LICENSE
Requires-Dist: typer>=0.9.0
Requires-Dist: rich>=13.7.0
Requires-Dist: jira>=3.5.1
Requires-Dist: google-generativeai>=0.3.2
Requires-Dist: questionary>=2.0.1
Dynamic: author
Dynamic: home-page
Dynamic: requires-python
